icm/__init__.py
icm/__main__.py
icm/commands/__init__.py
icm/commands/cmd_create.py
icm/commands/cmd_info.py
icm/commands/cmd_install.py
icm/commands/cmd_list.py
icm/commands/cmd_ls.py
icm/commands/cmd_rm.py
icm/commands/cmd_update.py
icm/commands/cmd_validate.py
icm/commons/__init__.py
icm/commons/commons.py
icm/commons/store.py
icm/resources/GPL-2.0
icm/resources/README.tpl.md
icm/resources/en.po
icm/resources/package.tpl.json
icm/resources/translation.tpl.js
icm-0.5.3.dist-info/entry_points.txt
icm-0.5.3.dist-info/LICENSE
icm-0.5.3.dist-info/WHEEL
icm-0.5.3.dist-info/METADATA
icm-0.5.3.dist-info/RECORD
