Metadata-Version: 2.1
Name: icm
Version: 0.5.3
Summary: Icestudio Collection Manager
Home-page: https://github.com/FPGAwars/icm
Author: Jesus Arroyo
Author-email: jesus.jkhlg@gmail.com 
Requires-Python: >=3.9
Classifier: Development Status :: 3 - Alpha
Classifier: Environment :: Console
Classifier: Intended Audience :: Developers
Classifier: License :: OSI Approved :: GNU General Public License v2 (GPLv2)
Classifier: Programming Language :: Python
Requires-Dist: click>=8.1.7
Requires-Dist: semantic_version>=2.10.0
Requires-Dist: polib>=1.2.0
Requires-Dist: requests>=2.32.3
Requires-Dist: tqdm>=4.66.4
